han2kip/__init__.py
han2kip/kip_converter.py
han2kip/data/dict.txt
han2kip/data/words.json
han2kip-0.1.2.dist-info/METADATA
han2kip-0.1.2.dist-info/WHEEL
han2kip-0.1.2.dist-info/licenses/LICENSE
han2kip-0.1.2.dist-info/RECORD
