Metadata-Version: 2.3
Name: han2kip
Version: 0.1.2
Summary: han2kip is a package for converting Taiwanese Hokkien Hanzi to its phonetic representation.
Project-URL: Homepage, https://github.com/juliaouo/han2kip
Author: 林怡萱, 林柏廷
License: MIT License
License-File: LICENSE
Classifier: License :: OSI Approved :: MIT License
Classifier: Operating System :: OS Independent
Classifier: Programming Language :: Python :: 3
Requires-Dist: jieba>=0.42.1
